eidein/__init__.py
eidein/eidein.py
eidein-0.0.0.dist-info/LICENSE
eidein-0.0.0.dist-info/METADATA
eidein-0.0.0.dist-info/WHEEL
eidein-0.0.0.dist-info/top_level.txt
eidein-0.0.0.dist-info/RECORD
