Metadata-Version: 2.1
Name: eidein
Version: 0.0.0
Summary: Interactive tool for dimensionality reduction of data and their visualisation.
Home-page: https://github.com/podondra/eidein
Author: Ondřej Podsztavek
Author-email: ondrej.podsztavek@gmail.com
License: UNKNOWN
Platform: UNKNOWN
Classifier: Development Status :: 1 - Planning
Classifier: Environment :: Web Environment
Classifier: Intended Audience :: Science/Research
Classifier: License :: OSI Approved :: GNU General Public License v3 (GPLv3)
Classifier: Operating System :: OS Independent
Classifier: Programming Language :: Python :: 3
Classifier: Topic :: Scientific/Engineering :: Visualization
Requires-Python: >=3.8
Requires-Dist: ipywidgets (>=7.5)
Requires-Dist: matplotlib (>=3.3)
Requires-Dist: scikit-learn (>=0.23)
Requires-Dist: umap (>=0.4)
